aiolib/__init__.py
aiolib/builtins.py
aiolib/itertools.py
aiolib-0.0.2.dist-info/DESCRIPTION.rst
aiolib-0.0.2.dist-info/METADATA
aiolib-0.0.2.dist-info/RECORD
aiolib-0.0.2.dist-info/WHEEL
aiolib-0.0.2.dist-info/entry_points.txt
aiolib-0.0.2.dist-info/metadata.json
aiolib-0.0.2.dist-info/top_level.txt
