Metadata-Version: 2.0
Name: aiolib
Version: 0.0.2
Summary: UNKNOWN
Home-page: https://github.com/feluxe/aiolib
Author: Felix Meyer-Wolters
Author-email: felix@meyerwolters.de
Maintainer: Felix Meyer-Wolters
Maintainer-email: felix@meyerwolters.de
License: unlicensed
Download-URL: https://github.com/feluxe/aiolib/tarball/0.0.2
Platform: 
Requires-Dist: aitertools
